identicallist/__init__.py
identicallist/identicallist.py
identicallist-0.1.2.dist-info/LICENSE
identicallist-0.1.2.dist-info/METADATA
identicallist-0.1.2.dist-info/WHEEL
identicallist-0.1.2.dist-info/top_level.txt
identicallist-0.1.2.dist-info/RECORD
