Metadata-Version: 2.1
Name: identicallist
Version: 0.1.2
Summary: A mutable list that allows only identical objects and inherits their properties and methods.
Home-page: https://gitlab.com/Thawn/identicallist
Author: thawn
Author-email: webmaster@korten.at
License: UNKNOWN
Platform: UNKNOWN
Classifier: Programming Language :: Python :: 3
Classifier: License :: OSI Approved :: MIT License
Classifier: Operating System :: OS Independent
Requires-Python: >=3.3
